mlopsantoinem/__init__.py
mlopsantoinem/main.py
mlopsantoinem-0.1.0.dist-info/METADATA
mlopsantoinem-0.1.0.dist-info/WHEEL
mlopsantoinem-0.1.0.dist-info/RECORD
